cookiesapi/__init__.py
cookiesapi/api_helper.py
cookiesapi/configuration.py
cookiesapi/cookiesapi_client.py
cookiesapi/decorators.py
cookiesapi/controllers/__init__.py
cookiesapi/controllers/base_controller.py
cookiesapi/controllers/brands_controller.py
cookiesapi/controllers/stores_controller.py
cookiesapi/controllers/strains_controller.py
cookiesapi/exceptions/__init__.py
cookiesapi/exceptions/api_exception.py
cookiesapi/exceptions/fault_response_exception.py
cookiesapi/http/__init__.py
cookiesapi/http/http_call_back.py
cookiesapi/http/http_client.py
cookiesapi/http/http_method_enum.py
cookiesapi/http/http_request.py
cookiesapi/http/http_response.py
cookiesapi/http/requests_client.py
cookiesapi/models/__init__.py
cookiesapi/models/address.py
cookiesapi/models/brand.py
cookiesapi/models/brand_asset.py
cookiesapi/models/brand_list.py
cookiesapi/models/brand_spec.py
cookiesapi/models/breeder.py
cookiesapi/models/color.py
cookiesapi/models/contact.py
cookiesapi/models/cookies_brand_enum.py
cookiesapi/models/dual_format_graphic.py
cookiesapi/models/error_detail.py
cookiesapi/models/error_info.py
cookiesapi/models/first_party_branding.py
cookiesapi/models/geo.py
cookiesapi/models/hours.py
cookiesapi/models/hours_range.py
cookiesapi/models/location.py
cookiesapi/models/material_info.py
cookiesapi/models/media_item.py
cookiesapi/models/media_key.py
cookiesapi/models/media_type.py
cookiesapi/models/name.py
cookiesapi/models/phone.py
cookiesapi/models/raster_graphic.py
cookiesapi/models/regular_hours.py
cookiesapi/models/responsive_graphic.py
cookiesapi/models/social_property.py
cookiesapi/models/species_enum.py
cookiesapi/models/store.py
cookiesapi/models/store_branding.py
cookiesapi/models/store_capability_enum.py
cookiesapi/models/store_key.py
cookiesapi/models/store_list.py
cookiesapi/models/store_media.py
cookiesapi/models/store_ordering.py
cookiesapi/models/store_social.py
cookiesapi/models/store_status_enum.py
cookiesapi/models/store_type_enum.py
cookiesapi-1.0.1.dist-info/LICENSE
cookiesapi-1.0.1.dist-info/METADATA
cookiesapi-1.0.1.dist-info/WHEEL
cookiesapi-1.0.1.dist-info/top_level.txt
cookiesapi-1.0.1.dist-info/RECORD
