Metadata-Version: 2.1
Name: cookiesapi
Version: 1.0.1
Summary: Python SDK for working with Cookies APIs.
Home-page: https://cookies.dev
Author: Eng@Cookies
Author-email: engineering@cookiescalifornia.com
License: UNKNOWN
Project-URL: Bug Tracker, https://github.com/CookiesCo/sdk-python/issues
Platform: UNKNOWN
Classifier: Programming Language :: Python :: 3
Classifier: License :: OSI Approved :: MIT License
Classifier: Operating System :: OS Independent
Requires-Python: >=3.6
License-File: LICENSE
